OperacionesSDGC/__init__.py
OperacionesSDGC/modulo.py
OperacionesSDGC-0.1.0.dist-info/METADATA
OperacionesSDGC-0.1.0.dist-info/WHEEL
OperacionesSDGC-0.1.0.dist-info/top_level.txt
OperacionesSDGC-0.1.0.dist-info/RECORD
